test_bayesian_average/__init__.py
test_bayesian_average/average.py
test_bayesian_average-0.0.3.dist-info/LICENSE.txt
test_bayesian_average-0.0.3.dist-info/METADATA
test_bayesian_average-0.0.3.dist-info/WHEEL
test_bayesian_average-0.0.3.dist-info/top_level.txt
test_bayesian_average-0.0.3.dist-info/RECORD
